MANIFEST.in
README.rst
requirements.txt
setup.py
us3/__init__.py
us3/us3.py
us3.egg-info/PKG-INFO
us3.egg-info/SOURCES.txt
us3.egg-info/dependency_links.txt
us3.egg-info/entry_points.txt
us3.egg-info/requires.txt
us3.egg-info/top_level.txt