Metadata-Version: 1.0
Name: us3
Version: 0.0.7
Summary: US3 helps you to manage files on AWS S3 or S3 compatible API like Ceph or Cleversafe
Home-page: https://github.com/ahmet2mir/python-us3.git
Author: Ahmet Demir
Author-email: me@ahmet2mir.eu
License: License :: OSI Approved :: Apache Software License
Keywords: s3,command line,cli
Platform: UNKNOWN
